Workbook

Sheet Rapport QA
A1: FIRONOVA — Rapport d'exécution E2E
A2: Exécuté par Claude (Cowork) — 27/09/2026 sur https://peptide-ca.preview.emergentagent.com (preview, mode test : délai de paiement 2 h).
A3: Commandes test créées : FN-260927-F5FE5701 (Interac, 259,98 $) et FN-260927-E9324C84 (crypto, 50,00 $), adresse 6995 rue Sagard, Montréal H2E 2S4, courriel qa.client1@example.com. À annuler en admin.
A5: Onglet | B5: Pass | C5: Fail | D5: Blocked | E5: N/A | F5: To test | G5: Total
A6: 1. Public site | B6: =COUNTIF('1. Public site'!$H:$H,"Pass") | C6: =COUNTIF('1. Public site'!$H:$H,"Fail") | D6: =COUNTIF('1. Public site'!$H:$H,"Blocked") | E6: =COUNTIF('1. Public site'!$H:$H,"N/A") | F6: =COUNTIF('1. Public site'!$H:$H,"To test") | G6: =COUNTA('1. Public site'!$A:$A)-1
A7: 2. Catalog & Products | B7: =COUNTIF('2. Catalog & Products'!$H:$H,"Pass") | C7: =COUNTIF('2. Catalog & Products'!$H:$H,"Fail") | D7: =COUNTIF('2. Catalog & Products'!$H:$H,"Blocked") | E7: =COUNTIF('2. Catalog & Products'!$H:$H,"N/A") | F7: =COUNTIF('2. Catalog & Products'!$H:$H,"To test") | G7: =COUNTA('2. Catalog & Products'!$A:$A)-1
A8: 3. Cart & Checkout | B8: =COUNTIF('3. Cart & Checkout'!$H:$H,"Pass") | C8: =COUNTIF('3. Cart & Checkout'!$H:$H,"Fail") | D8: =COUNTIF('3. Cart & Checkout'!$H:$H,"Blocked") | E8: =COUNTIF('3. Cart & Checkout'!$H:$H,"N/A") | F8: =COUNTIF('3. Cart & Checkout'!$H:$H,"To test") | G8: =COUNTA('3. Cart & Checkout'!$A:$A)-1
A9: 4. Payments & Confirmation | B9: =COUNTIF('4. Payments & Confirmation'!$H:$H,"Pass") | C9: =COUNTIF('4. Payments & Confirmation'!$H:$H,"Fail") | D9: =COUNTIF('4. Payments & Confirmation'!$H:$H,"Blocked") | E9: =COUNTIF('4. Payments & Confirmation'!$H:$H,"N/A") | F9: =COUNTIF('4. Payments & Confirmation'!$H:$H,"To test") | G9: =COUNTA('4. Payments & Confirmation'!$A:$A)-1
A10: 5. Account & Authentication | B10: =COUNTIF('5. Account & Authentication'!$H:$H,"Pass") | C10: =COUNTIF('5. Account & Authentication'!$H:$H,"Fail") | D10: =COUNTIF('5. Account & Authentication'!$H:$H,"Blocked") | E10: =COUNTIF('5. Account & Authentication'!$H:$H,"N/A") | F10: =COUNTIF('5. Account & Authentication'!$H:$H,"To test") | G10: =COUNTA('5. Account & Authentication'!$A:$A)-1
A11: 6. Legal & Info pages | B11: =COUNTIF('6. Legal & Info pages'!$H:$H,"Pass") | C11: =COUNTIF('6. Legal & Info pages'!$H:$H,"Fail") | D11: =COUNTIF('6. Legal & Info pages'!$H:$H,"Blocked") | E11: =COUNTIF('6. Legal & Info pages'!$H:$H,"N/A") | F11: =COUNTIF('6. Legal & Info pages'!$H:$H,"To test") | G11: =COUNTA('6. Legal & Info pages'!$A:$A)-1
A12: 7. Affiliates (client) | B12: =COUNTIF('7. Affiliates (client)'!$H:$H,"Pass") | C12: =COUNTIF('7. Affiliates (client)'!$H:$H,"Fail") | D12: =COUNTIF('7. Affiliates (client)'!$H:$H,"Blocked") | E12: =COUNTIF('7. Affiliates (client)'!$H:$H,"N/A") | F12: =COUNTIF('7. Affiliates (client)'!$H:$H,"To test") | G12: =COUNTA('7. Affiliates (client)'!$A:$A)-1
A13: 8. Admin — General & Dashboard | B13: =COUNTIF('8. Admin — General & Dashboard'!$H:$H,"Pass") | C13: =COUNTIF('8. Admin — General & Dashboard'!$H:$H,"Fail") | D13: =COUNTIF('8. Admin — General & Dashboard'!$H:$H,"Blocked") | E13: =COUNTIF('8. Admin — General & Dashboard'!$H:$H,"N/A") | F13: =COUNTIF('8. Admin — General & Dashboard'!$H:$H,"To test") | G13: =COUNTA('8. Admin — General & Dashboard'!$A:$A)-1
A14: 9. Orders & Fulfillment | B14: =COUNTIF('9. Orders & Fulfillment'!$H:$H,"Pass") | C14: =COUNTIF('9. Orders & Fulfillment'!$H:$H,"Fail") | D14: =COUNTIF('9. Orders & Fulfillment'!$H:$H,"Blocked") | E14: =COUNTIF('9. Orders & Fulfillment'!$H:$H,"N/A") | F14: =COUNTIF('9. Orders & Fulfillment'!$H:$H,"To test") | G14: =COUNTA('9. Orders & Fulfillment'!$A:$A)-1
A15: 10. Admin — Products & Stock | B15: =COUNTIF('10. Admin — Products & Stock'!$H:$H,"Pass") | C15: =COUNTIF('10. Admin — Products & Stock'!$H:$H,"Fail") | D15: =COUNTIF('10. Admin — Products & Stock'!$H:$H,"Blocked") | E15: =COUNTIF('10. Admin — Products & Stock'!$H:$H,"N/A") | F15: =COUNTIF('10. Admin — Products & Stock'!$H:$H,"To test") | G15: =COUNTA('10. Admin — Products & Stock'!$A:$A)-1
A16: 11. Admin — Coupons & Customers | B16: =COUNTIF('11. Admin — Coupons & Customers'!$H:$H,"Pass") | C16: =COUNTIF('11. Admin — Coupons & Customers'!$H:$H,"Fail") | D16: =COUNTIF('11. Admin — Coupons & Customers'!$H:$H,"Blocked") | E16: =COUNTIF('11. Admin — Coupons & Customers'!$H:$H,"N/A") | F16: =COUNTIF('11. Admin — Coupons & Customers'!$H:$H,"To test") | G16: =COUNTA('11. Admin — Coupons & Customers'!$A:$A)-1
A17: 12. Affiliates & Payouts | B17: =COUNTIF('12. Affiliates & Payouts'!$H:$H,"Pass") | C17: =COUNTIF('12. Affiliates & Payouts'!$H:$H,"Fail") | D17: =COUNTIF('12. Affiliates & Payouts'!$H:$H,"Blocked") | E17: =COUNTIF('12. Affiliates & Payouts'!$H:$H,"N/A") | F17: =COUNTIF('12. Affiliates & Payouts'!$H:$H,"To test") | G17: =COUNTA('12. Affiliates & Payouts'!$A:$A)-1
A18: 13. Admin — System | B18: =COUNTIF('13. Admin — System'!$H:$H,"Pass") | C18: =COUNTIF('13. Admin — System'!$H:$H,"Fail") | D18: =COUNTIF('13. Admin — System'!$H:$H,"Blocked") | E18: =COUNTIF('13. Admin — System'!$H:$H,"N/A") | F18: =COUNTIF('13. Admin — System'!$H:$H,"To test") | G18: =COUNTA('13. Admin — System'!$A:$A)-1
A19: 14. Non-functional | B19: =COUNTIF('14. Non-functional'!$H:$H,"Pass") | C19: =COUNTIF('14. Non-functional'!$H:$H,"Fail") | D19: =COUNTIF('14. Non-functional'!$H:$H,"Blocked") | E19: =COUNTIF('14. Non-functional'!$H:$H,"N/A") | F19: =COUNTIF('14. Non-functional'!$H:$H,"To test") | G19: =COUNTA('14. Non-functional'!$A:$A)-1
A20: TOTAL | B20: =SUM(B6:B19) | C20: =SUM(C6:C19) | D20: =SUM(D6:D19) | E20: =SUM(E6:E19) | F20: =SUM(F6:F19) | G20: =SUM(G6:G19)
A22: CORRECTIONS À FAIRE (par priorité)
A23: # | B23: Priorité | C23: Zone | D23: Problème constaté | E23: Correction proposée | F23: Tests liés | G23: Statut correction | H23: Détail de la correction
A24: 1 | B24: Critique | C24: Paiement Interac | D24: Question de sécurité en anglais 'What is the brand name? (lowercase)' et réponse 'nordpep' (ancienne marque) sur la page de confirmation. | E24: Remplacer la réponse (ex. 'fironova'), traduire la question FR/EN, vérifier aussi le courriel d'instructions. | F24: PM-002 | G24: Corrigé | H24: Question stockée en FR et EN ; réponse = INTERAC_PASSWORD_HINT (défaut « FIRONOVA »). L'écran choisit sa langue, les anciennes commandes retombent sur la clé anglaise.
A25: 2 | B25: Critique | C25: Sécurité admin | D25: Bouton OPS visible par tous les visiteurs ; le clic mène à /login?next=%2Fops-portal-fn7k2q, ce qui révèle le chemin secret de l'admin. | E25: N'afficher OPS qu'aux comptes admin/staff connectés ; ne jamais mettre le chemin secret dans ?next= (utiliser un alias neutre comme /ops). | F25: SP-014, NF-006 | G25: Laissé tel quel | H25: Décision de Mireille : OPS reste inchangé pour l'instant.
A26: 3 | B26: Majeur | C26: Checkout | D26: Validation : le bouton s'active avec l'adresse vide, puis une seule erreur à la fois en toast ('Nom est requis' alors que c'est Prénom qui manque). | E26: Afficher une erreur sous chaque champ requis, faire défiler jusqu'au premier champ en erreur, corriger les libellés et l'accord ('Adresse est requise'). | F26: PA-008, PA-006 | G26: Corrigé | H26: Erreur sous chaque champ requis + défilement jusqu'au premier champ en erreur.
A27: 4 | B27: Majeur | C27: Checkout | D27: Le résumé et le total utilisent le prix stocké dans le panier (localStorage). Un prix modifié s'affiche (210,99 $) alors que le serveur facture le vrai prix (259,98 $). | E27: Recharger prix/stock depuis l'API à l'ouverture du checkout et du panier. La sécurité côté serveur est OK. | F27: PA-019 | G27: Corrigé | H27: Nouvelle route POST /api/cart/revalidate : le panier relit prix, stock et SKU auprès du serveur à chaque ouverture. Une panne réseau ne vide pas le panier.
A28: 5 | B28: Majeur | C28: AgeGate | D28: La confirmation 19+ est mémorisée dans localStorage (fironova_age_confirmed=1) : le gate ne réapparaît pas au rechargement, contrairement à la règle du plan. | E28: Décider de la règle. Si 'non persisté' : garder l'état en mémoire. Sinon, mettre à jour le plan. | F28: SP-004 | G28: Corrigé | H28: La confirmation 19+ n'est plus persistée : l'état vit en mémoire, chaque chargement repose la question.
A29: 6 | B29: Majeur | C29: Stock | D29: Le stock au niveau produit ne correspond pas aux variantes (Épitalon 85 vs 59, CJC 100 vs 96, BPC 58 vs 56, Ipamoréline 147 vs 148). Aucun indicateur 'stock bas'. | E29: Calculer le stock produit comme la somme des variantes (ou le masquer) ; afficher un indicateur stock bas/rupture. | F29: CA-008 | G29: Corrigé | H29: _stock_produit_coherent() : le stock produit = somme des variantes, plus l'indicateur stock_low.
A30: 7 | B30: Majeur | C30: Panier | D30: Le panier affiche le SKU 'BPC-157-5MG' pour la variante 10 mg. Le SKU du 5 mg vaut 'BPC-157-5MG5' (faute de frappe). | E30: Afficher le SKU de la variante choisie ; corriger la donnée BPC-157-5MG5 → BPC-157-5MG. | F30: PA-001, CA-004 | G30: Corrigé | H30: Le panier stocke et affiche variant_sku (le SKU de la variante choisie) ; les lignes anciennes se réparent à la première revalidation.
A31: 8 | B31: Majeur | C31: Performance | D31: Chaque photo produit PNG pèse 2,6 à 2,8 Mo : grilles blanches pendant le chargement. | E31: Convertir en WebP/AVIF (~150 Ko), ajouter srcset/lazy-loading. | F31: NF-004 | G31: Partiel | H31: lazy-loading, decoding async et width/height sont en place. Reste la conversion WebP/AVIF des PNG de 2,6 Mo : traitement d'images, hors code.
A32: 9 | B32: Majeur | C32: Navigation | D32: Aucun lien vers /about dans le header, le menu mobile ni le footer (seulement le bouton 'Nos standards' de l'accueil). | E32: Ajouter 'À propos' au menu et au footer. | F32: SP-007 | G32: Corrigé | H32: « À propos » présent dans le header et le footer.
A33: 10 | B33: Majeur | C33: Newsletter | D33: Après inscription, message 'Confirmé : vous êtes inscrit.' alors que la règle est le double opt-in. | E33: Message 'Vérifiez votre courriel pour confirmer' ; vérifier l'envoi du lien /newsletter/confirm. | F33: AU-015 | G33: Corrigé | H33: Message FR/EN remplacé par « Vérifiez votre courriel pour confirmer votre inscription ».
A34: 11 | B34: Mineur | C34: Catalogue | D34: Le tri 'Prix ↑' ignore le prix promo (GHK-Cu à 30 $ classé après 44,99 $). 'Souvent recherché avec' affiche le prix sans promo (Tirzépatide 259,99 au lieu de 200). | E34: Trier et afficher selon le prix effectif (promo si présente). | F34: CA-003, CA-004 | G34: Corrigé | H34: Tri et affichage sur le prix effectif (promo prise en compte).
A35: 12 | B35: Mineur | C35: Mobile | D35: /catalog à 360px : débordement horizontal (408px) causé par le libellé 'PRÉCOMMANDE' d'une carte. | E35: Autoriser le retour à la ligne / tronquer ce libellé. | F35: NF-001 | G35: Corrigé | H35: Chasse resserrée sur mobile + break-words : « PRÉCOMMANDE » ne pousse plus la grille à 408 px.
... A44: 21 | B44: Plan de test | C44: Mise à jour du plan | D44: Plusieurs attentes du plan sont obsolètes : LE-002 '2 pm ET / 7 sous-sections' (site : 13 h / 8), LE-003 '11 sections' (12), LE-004 '22 questions / info@nordpep.ca' (23 / info@fironova.com), SP-009 rubrique 'Information' (site : 'Légal'), SP-014 bouton 'ADMIN' (site : 'OPS'). | E44: Mettre le plan à jour. | F44: LE-002, LE-003, LE-004, SP-009, SP-014 | G44: Corrigé | H44: Les deux plans (EN + FR) mis à jour : LE-002 (8 sous-sections, 13 h HE), LE-003 (12 sections), LE-004 (23 questions, info@fironova.com), SP-009 (rubrique « Légal »), SP-014 (bouton OPS).

Sheet Rules & guidelines
B1: FIRONOVA — E2E TEST PLAN
B2: Research peptide store · bilingual FR/EN · Canada compliance (19+)
B4: BUSINESS RULES (verified against the code on 2026-09-23)
B5: • 19+ restriction: age gate on first visit, not persisted.
B6: • 'Research use only' products: bilingual regulatory notice on every product page.
B7: • Payments: Interac e-Transfer and crypto via NOWPayments (widget + HMAC webhook).
B8: • Payment window: PER ORDER (payment_ttl_hours, frozen at purchase). Normal default 0.5 h (30 min), as promised by the Compliance and FAQ pages. In test mode the server applies 2 h. The banner shows the real delay; countdown refreshes every 15 s.
B9: • Shipping: flat $20 CAD under $200, FREE from $200 (FREE_SHIPPING_THRESHOLD_CAD).
B10: • Cutoff hour: DECIDED on 2026-09-23 — it is 1:00 p.m. ET. The Compliance and FAQ pages were corrected (2:00 p.m. → 1:00 p.m.) and the code applies ORDER_CUTOFF_HOUR=13 by default. Both say the same thing.
B11: • Admin portal behind a secret path (e.g. /ops-portal-fn7k2q), never indexed.
B12: • Coupons: % or fixed amount, min_subtotal, usage_limit, expires_at, auto-counted usage.
B13: • Affiliates: email invitation (magic-link), FN+6 codes, per-affiliate discount, tier on the last 12 CLOSED months (floor set on the 1st) + immediate climb measured on the 11-month + current-month FORECAST (what you climb, you keep on the 1st) — 2026-09-27, $25 payout threshold.
... B28: • Dedicated test MongoDB; test accounts in the 'Test accounts' tab.

Sheet Corrections
A1: Where | B1: Old text (excerpt) | C1: New text (excerpt) | D1: Why (code-verified)
A2: Instructions — L21 | B2: • Unpaid orders are auto-cancelled after 48 h (countdown banner on the confirmation page). | C2: • Unpaid orders are cancelled after THAT ORDER's payment window (payment_ttl_hours, frozen at purchase). Normal default: 0.5 h (30 min), | D2: The code no longer contains any '48 h' payment window. The banner reads payment_ttl_hours (commit 358361d).
A3: 4. Payments & Confirmation — L6 | B3: 48 h payment-required banner | C3: Payment-required banner (per-order delay) | D3: The banner reads the real per-order delay.
A4: 4. Payments & Confirmation — L6 | B4: 'Payment required within 48 hours' + countdown (30 s tick). | C4: 'Payment required within X' where X is the order's REAL delay (e.g. '30 minutes' in production). Countdown tick: 15 s. | D4: delaiLisible reads payment_ttl_hours; tick is 15000 ms in OrderConfirmation.jsx.
A5: 4. Payments & Confirmation — L7 | B5: 1. Wait 30 s. 2. Observe. | C5: 1. Wait 15 s. 2. Observe. | D5: setInterval(tick, 15000).
A6: 4. Payments & Confirmation — L12 | B6: Auto-cancel unpaid order (48 h) | C6: Auto-cancel unpaid order (per-order delay) | D6: The watchdog cancels after the order's own payment_ttl_hours.
A7: 2. Catalog & Products — L6 | B7: COA Verified / Pending badge | C7: Certificate of analysis (COA) on the product page | D7: The public badge no longer exists (removed 2026-09-20).
A8: 2. Catalog & Products — L6 | B8: 1. Open a product with COA. 2. Click the badge. | C8: 1. Open a product with an available COA. 2. Find the download button under the price. | D8: Nothing is shown under the photo anymore.
A9: 2. Catalog & Products — L6 | B9: Green 'COA Verified' (or orange 'Pending') badge linking to the PDF. | C9: COA available: 'Certificate of analysis / Lab report' button (PDF link). COA pending: 'COA to come' notice. No badge under the photo. | D9: The COA pills were removed from the image column; the state reads in the purchase column.
A10: 2. Catalog & Products — L3 | B10: 3 airy columns (gap-8 lg:gap-12) with featured products only. | C10: 2 columns on mobile, 3 on small screens, 4 on large (gap-3 / sm:gap-5 / lg:gap-6). | D10: The grid was tightened for mobile on 2026-09-23 (commit 4348265).
A11: 2. Catalog & Products — L7 | B11: Out-of-stock product (preorder_allowed) | C11: Out-of-stock VARIANT with pre-order (preorder_enabled) | D11: The field is preorder_enabled, at VARIANT level.
A12: 2. Catalog & Products — L5 | B12: Opens /product/:slug with name, price, description, images, add-to-cart button. | C12: Opens /product/:slug with name, price, images, add-to-cart button. | D12: The free-form description is no longer published on the product page.
... A22: 1. Public site — checkout | B22: Many confirmation checkboxes | C22: Reduced checkboxes; two-column layout on desktop | D22: Checkout redesign 2026-09 (Mireille requests).

Sheet Test accounts
A1: Account | B1: Email address | C1: Role | D1: Reusable? | E1: Used in tests
A2: GMAIL TIP: all these accounts land in a single real inbox if the tester uses the '+alias' trick — e.g. tester+client1@gmail.com is received in tester@gmail.com. No extra Gmail account to create.
A3: Admin | B3: tester+admin@gmail.com | C3: Administrator | D3: Yes | E3: AD-001→013 · CO-* · PR-* · CP-* · AF-101→113 · SY-*
A4: Staff | B4: tester+staff@gmail.com | C4: Staff (limited permissions) | D4: Yes | E4: SY-001 · SY-002
A5: Client1 | B5: tester+client1@gmail.com | C5: Main customer | D5: Yes | E5: AU-002→004 · AU-008→014 · SP-011 · AD-003 · PA-018
A6: Client2 | B6: tester+client2@gmail.com | C6: Second customer | D6: Yes | E6: AF-007 (order via ?ref=)
A7: New client | B7: tester+new@gmail.com | C7: Blank account (signup) | D7: Yes (after creation) | E7: AU-001
A8: Brute-force client | B8: tester+bruteforce@gmail.com | C8: Login lockout test | D8: Reusable (reset password) | E8: AU-005 · AU-006
A9: Newsletter client | B9: tester+newsletter@gmail.com | C9: Newsletter opt-in | D9: Yes | E9: AU-015
A10: Google client | B10: Tester's real Gmail address | C10: OAuth login | D10: Yes | E10: AU-007
A11: Affiliate1 | B11: tester+affiliate1@gmail.com | C11: Main affiliate (with sales) | D11: Yes | E11: AF-004→005 · AF-007→010
A12: Affiliate2 | B12: tester+affiliate2@gmail.com | C12: Affiliate with no sale (fallback) | D12: Yes | E12: AF-006
A13: Affiliate3 | B13: tester+affiliate3@gmail.com | C13: Individual invitation | D13: Yes | E13: AF-001 · AF-002 · AF-101 · AF-104 · AF-107
A14: Affiliate4 | B14: tester+affiliate4@gmail.com | C14: Alias / percent rename test | D14: Yes | E14: AF-105 · AF-106
... A16: Payout affiliate | B16: tester+affiliatepayout@gmail.com | C16: Commissions (payouts) | D16: Yes | E16: AF-108→113

Sheet 1. Public site
A1: ID | B1: Module | C1: Test case / Scenario | D1: Preconditions / Data | E1: Account required | F1: Steps | G1: Expected result | H1: Status | I1: Priority | J1: Severity | K1: Actual result | L1: Comments
A2: SP-001 | B2: Home / AgeGate | C2: 19+ gate appears on first visit | D2: Cleared cache/localStorage | E2: — | F2: 1. Open the site. 2. Observe the AgeGate overlay. | G2: Full-screen 'RESTRICTED · FIRONOVA' overlay + 19+ badge, confirm/exit buttons visible. | H2: Pass | I2: High | J2: Blocker | K2: Overlay 'RESTRICTED · FIRONOVA' + 19+ + boutons Confirmer/Quitter affichés (après suppression de fironova_age_confirmed). | L2: Le texte du gate est en FR seulement même si l'interface était en EN (ligne de bas bilingue). Flèche du bouton principal coincée contre le bord (cosmétique). [Claude (Cowork) — 27/09/2026]
A3: SP-002 | B3: Home / AgeGate | C3: Age confirmation accepted | D3: AgeGate displayed | E3: — | F3: 1. Click 'I am 19+ / Enter'. | G3: Overlay disappears, site is accessible, scrolling restored. | H3: Pass | I3: High | J3: Blocker | K3: Clic 'J'ai 19 ans ou plus' : overlay disparaît, body overflow repasse à visible. | L3: [Claude (Cowork) — 27/09/2026]
A4: SP-003 | B4: Home / AgeGate | C4: Age refusal (exit) | D4: AgeGate displayed | E4: — | F4: 1. Click 'Exit / Leave'. | G4: Terminal refusal screen (no back link), no site access. | H4: Pass | I4: High | J4: Major | K4: Écran 'Accès non disponible' sans lien de retour. | L4: Mais le site reste rendu dessous : Tab atteint les boutons du header (lang-toggle) derrière l'écran de refus. Aucun piège de focus. Rechargement = gate de nouveau (refus non mémorisé). [Claude (Cowork) — 27/09/2026]
A5: SP-004 | B5: Home / AgeGate | C5: AgeGate reappears on reload | D5: AgeGate confirmed then reload | E5: — | F5: 1. Confirm age. 2. Reload (F5). | G5: AgeGate overlay shows again (not persisted). | H5: Fail | I5: Medium | J5: Minor | K5: Après confirmation, localStorage.fironova_age_confirmed='1' et le gate NE réapparaît PAS au rechargement. | L5: Contredit la règle 'not persisted'. Soit changer la règle, soit utiliser un état en mémoire/sessionStorage. [Claude (Cowork) — 27/09/2026]
A6: SP-005 | B6: Home / AgeGate | C6: Overlay blocks scrolling | D6: AgeGate displayed | E6: — | F6: 1. Try to scroll under the overlay. | G6: Background page does not scroll while the question is pending. | H6: Fail | I6: Low | J6: Minor | K6: Gate affiché : body overflow=hidden mais <html> défile quand même (scrollY 0 → 500 à la molette). | L6: Mettre overflow:hidden sur html aussi (ou position:fixed sur body). [Claude (Cowork) — 27/09/2026]
A7: SP-006 | B7: Navigation | C7: Compliance band at the top | D7: Site loaded | E7: — | F7: 1. Observe the top bar (above header). | G7: Bilingual compliance band ('research use only', 19+) visible. | H7: Pass | I7: High | J7: Major | K7: Bandeau de conformité présent au-dessus du header, traduit selon la langue (FR : 'Usage en laboratoire uniquement · … · 19+ seulement' / EN : 'For laboratory research use only · … · 19+ only'). | L7: [Claude (Cowork) — 27/09/2026]
A8: SP-007 | B8: Navigation | C8: Main menu (header) | D8: Site loaded | E8: — | F8: 1. Check menu items: Catalog, About, (Lab if enabled). | G8: Links present and working to /catalog, /about (and /lab if COA_PAGE_ENABLED). | H8: Fail | I8: High | J8: Major | K8: Header : seulement 'Catalogue' (+ OPS, langue, panier, menu). Menu burger : Catalogue, OPS, Connexion. Aucun lien vers /about dans le header, le menu ni le footer. | L8: /about n'est accessible que via le bouton 'Nos standards' de l'accueil. /lab redirige vers l'accueil (flag désactivé). [Claude (Cowork) — 27/09/2026]
A9: SP-008 | B9: Navigation | C9: FR ↔ EN language toggle | D9: Site loaded | E9: — | F9: 1. Click the language selector. 2. Check page content. | G9: Whole UI switches to English and back to French without hard reload. | H9: Pass | I9: High | J9: Major | K9: Bascule FR↔EN sans rechargement (marqueur JS conservé), lang du <html> mis à jour, aucun texte FR résiduel en EN sur 15 routes. | L9: [Claude (Cowork) — 27/09/2026]
A10: SP-009 | B10: Navigation | C10: Footer link → Terms & Conditions | D10: Site loaded | E10: — | F10: 1. Scroll to footer. 2. 'Information' → 'Terms & Conditions'. | G10: Opens /compliance; 'Compliance/Legal' wording absent from top menu. | H10: Pass | I10: Medium | J10: Minor | K10: Footer 'Légal' → 'Conditions' ouvre /compliance ; aucun libellé Compliance/Legal dans le menu du haut. | L10: La rubrique du footer s'appelle 'LÉGAL' et non 'Information' comme dans le plan. [Claude (Cowork) — 27/09/2026]
A11: SP-010 | B11: Navigation | C11: Footer pages (Privacy, FAQ) | D11: Site loaded | E11: — | F11: 1. Open 'Privacy Policy'. 2. Open 'FAQ'. | G11: /privacy and /faq load correctly, bilingual, no 404. | H11: Pass | I11: Medium | J11: Minor | K11: /privacy et /faq chargent, en FR et EN, sans 404. | L11: [Claude (Cowork) — 27/09/2026]
A12: SP-011 | B12: Navigation | C12: Dark mode (account & admin) | D12: Logged-in user | E12: Client1 | F12: 1. Log in. 2. Toggle theme. | G12: Night mode applies to /account and admin (not the public store). Readable contrast. | H12: To test | I12: Low | J12: Minor
A13: SP-012 | B13: Navigation | C13: Cookie consent banner | D13: Cleared cache | E13: — | F13: 1. Open the site. 2. Observe cookie banner. | G13: Consent banner visible and actionable (accept/decline). | H13: Fail | I13: Low | J13: Minor | K13: Aucune bannière de consentement aux cookies, même après effacement de l'état. Aucun texte 'cookie/témoin' sur le site. | L13: Si le site n'utilise que des cookies essentiels, documenter ce choix et passer le test en N/A. Sinon, bannière requise (Loi 25). [Claude (Cowork) — 27/09/2026]
A14: SP-013 | B14: Navigation | C14: 404 page (unknown route) | D14: Site loaded | E14: — | F14: 1. Navigate to a non-existent URL (/xyz). | G14: Clean 'NotFound' page, no blocking console errors, link back home. | H14: Pass | I14: Low | J14: Minor | K14: /page-inexistante : page '// 404 · Page not found' + bouton Home, aucune erreur console. | L14: [Claude (Cowork) — 27/09/2026]
A15: SP-014 | B15: Navigation | C15: ADMIN button in header | D15: Site loaded, logged out | E15: — | F15: 1. Click ADMIN. | G15: Redirects to /login?next=... (admin stays protected). | H15: Fail | I15: Medium | J15: Major | K15: Déconnecté, clic sur OPS → /login?next=%2Fops-portal-fn7k2q (écran 'Fironova OPS'). L'admin reste protégé. | L15: Le bouton OPS est visible par tous les visiteurs ET l'URL de redirection révèle le chemin secret /ops-portal-fn7k2q. Masquer le bouton aux non-admins et ne pas mettre le chemin dans ?next=. [Claude (Cowork) — 27/09/2026]

Sheet 2. Catalog & Products
A1: ID | B1: Module | C1: Test case / Scenario | D1: Preconditions / Data | E1: Account required | F1: Steps | G1: Expected result | H1: Status | I1: Priority | J1: Severity | K1: Actual result | L1: Comments
A2: CA-001 | B2: Catalog | C2: Product listing | D2: Seeded products | E2: — | F2: 1. Open /catalog. | G2: All products displayed (image, name, price, stock status). | H2: Pass | I2: High | J2: Blocker | K2: /catalog : 12 produits avec image, nom, prix, statut de stock et bouton d'ajout. | L2: Carte BPC-157 : badge 'PRÉCOMMANDE' ET 'EN STOCK' à la fois (5 mg en stock, 10 mg en précommande) : c'est ambigu. 'DÈS' est placé après le prix. [Claude (Cowork) — 27/09/2026]
A3: CA-002 | B3: Catalog | C3: 'Featured' filter / featured compounds | D3: 6 'featured' products seeded | E3: — | F3: 1. Home → 'Featured Compounds' section. | G3: 2 columns on mobile, 3 on small screens, 4 on large (gap-3 / sm:gap-5 / lg:gap-6). | H3: Pass | I3: Medium | J3: Major | K3: Grille : 2 col/12px à 360px, 3 col/20px à 768px, 4 col/24px à 1280 et 1600px (conforme gap-3/sm:gap-5/lg:gap-6). | L3: L'accueil n'affiche que 4 produits vedettes alors que 6 sont marqués featured (Sémaglutide et Tirzépatide absents). La 3e carte (GHK-Cu) utilise une photo générique au lieu du flacon Fironova. [Claude (Cowork) — 27/09/2026]
A4: CA-003 | B4: Catalog | C4: Product search / sort | D4: Catalog loaded | E4: — | F4: 1. Use search and sort (price, name). | G4: Results filter/sort correctly, no errors. | H4: Fail | I4: Medium | J4: Minor | K4: Recherche OK ('tirz' → Tirzépatide, 'semaglutide' sans accent OK, 'zzzz' → message 'Aucun résultat'). Tri Nom et Prix ↓ OK. | L4: Tri Prix ↑ ignore le prix promo : GHK-Cu (promo 30 $) classé après Mélanotan II (44,99 $), trié sur 49,99 $. [Claude (Cowork) — 27/09/2026]
A5: CA-004 | B5: Product page | C5: Access product page | D5: Existing product | E5: — | F5: 1. Click a product. | G5: Opens /product/:slug with name, price, images, add-to-cart button. | H5: Pass | I5: High | J5: Blocker | K5: /product/bpc-157-5mg : nom, prix, images, fiche technique, bouton d'ajout. | L5: Les produits suggérés ('Souvent recherché avec') affichent le prix normal, sans la promo (Tirzépatide 259,99 $ au lieu de 200 $). SKU du 5 mg dans les données = 'BPC-157-5MG5' (faute de frappe probable). [Claude (Cowork) — 27/09/2026]
A6: CA-005 | B6: Product page | C6: Certificate of analysis (COA) on the product page | D6: Product with coa_url | E6: — | F6: 1. Open a product with an available COA. 2. Find the download button under the price. | G6: COA available: 'Certificate of analysis / Lab report' button (PDF link). COA pending: 'COA to come' notice. No badge under the photo. | H6: Pass | I6: Medium | J6: Minor | K6: 5 mg : bouton 'Télécharger le COA / rapport' sous le prix. 10 mg : mention 'COA à venir' + encadré explicatif. Aucun badge sous la photo. | L6: Les URL de COA sont des liens tiers de test : BPC-157 → visionneuse PDF de digital-media.fao.org, GHK-Cu → peptidetestcanada.ca/verify. À remplacer par les vrais PDF. 'Lot actuel' affiche '-'. [Claude (Cowork) — 27/09/2026]
A7: CA-006 | B7: Product page | C7: Pre-order badge & flow | D7: Out-of-stock VARIANT with pre-order (preorder_enabled) | E7: — | F7: 1. Open an out-of-stock product allowed for pre-order. | G7: 'Pre-order' badge shown, add-to-cart possible without decrementing stock below 0. | H7: Pass | I7: Medium | J7: Major | K7: BPC-157 10 mg (stock 0, preorder_enabled) : 'Précommande · Rupture', bouton 'PRÉCOMMANDE · $85.00', ajout au panier possible. | L7: Libellé contradictoire 'Précommande · Rupture'. Décrément du stock à vérifier après commande (voir PM). La mention précommande n'apparaît pas dans le panier ni dans le résumé du checkout. [Claude (Cowork) — 27/09/2026]
A8: CA-007 | B8: Product page | C8: Out-of-stock — add disabled | D8: Out-of-stock product, no pre-order | E8: — | F8: 1. Open the product. | G8: 'Add to cart' button disabled. | H8: Blocked | I8: High | J8: Major | K8: Aucun produit en rupture sans précommande dans les données actuelles. | L8: À créer en admin (stock 0, preorder désactivé) pour tester. [Claude (Cowork) — 27/09/2026]
A9: CA-008 | B9: Product page | C9: Stock indicator (low/out) | D9: Products with thresholds | E9: — | F9: 1. Open several products. | G9: Low-stock / out / numeric indicators consistent with real stock. | H9: Fail | I9: Medium | J9: Minor | K9: Toutes les fiches affichent seulement 'EN STOCK' (aucun indicateur de stock bas ou numérique). Le stock produit ne correspond pas à la somme des variantes : Épitalon 85 vs 59, CJC-1295 100 vs 96, BPC-157 58 vs 56, Ipamoréline 147 vs 148. | L9: Le champ stock au niveau produit n'est pas synchronisé avec les variantes. [Claude (Cowork) — 27/09/2026]
A10: CA-009 | B10: Product page | C10: Variant selection (5mg/10mg…) | D10: Product with variants | E10: — | F10: 1. Change variant. | G10: Price and stock update according to the selected variant. | H10: Pass | I10: Medium | J10: Major | K10: Passage 5 mg → 10 mg : prix (64,99 → 85,00 $ avec prix barré 100 $), SKU (BPC-157-10MG) et statut (précommande) mis à jour. | L10: Format '5.0mg' / '10.0mg' (décimale inutile). [Claude (Cowork) — 27/09/2026]

Sheet 3. Cart & Checkout
A1: ID | B1: Module | C1: Test case / Scenario | D1: Preconditions / Data | E1: Account required | F1: Steps | G1: Expected result | H1: Status | I1: Priority | J1: Severity | K1: Actual result | L1: Comments
A2: PA-001 | B2: Cart | C2: Add a product to cart | D2: Empty cart | E2: — | F2: 1. Add a product. 2. Open the cart drawer. | G2: Cart counter increments, item appears in drawer with price. | H2: Pass | I2: High | J2: Blocker | K2: Ajout depuis le catalogue et la fiche : compteur du header incrémenté, article dans le tiroir avec son prix. Toast 'Ajouté au panier' avec Continuer / Voir le panier. | L2: Le panier affiche le SKU 'BPC-157-5MG' pour la variante 10 mg (mauvais SKU). Les boutons +/− n'ont pas de nom accessible. [Claude (Cowork) — 27/09/2026]
A3: PA-002 | B3: Cart | C3: Change quantities | D3: Item in cart | E3: — | F3: 1. Increase/decrease quantity. | G3: Subtotal recalculated in real time. | H3: Pass | I3: High | J3: Major | K3: +/− dans le tiroir : sous-total recalculé instantanément (85 → 255 $ pour 3). | L3: [Claude (Cowork) — 27/09/2026]
A4: PA-003 | B4: Cart | C4: Remove an item | D4: Item in cart | E4: — | F4: 1. Remove the item. | G4: Item removed; empty cart shows $0 total. | H4: Pass | I4: High | J4: Major | K4: Suppression → 'Votre panier est vide' + bouton 'Parcourir les composés'. localStorage vidé. | L4: Aucun total à 0 $ affiché (écran vide à la place). Acceptable. [Claude (Cowork) — 27/09/2026]
A5: PA-004 | B5: Cart | C5: Cart persistence (reload) | D5: Item in cart | E5: — | F5: 1. Reload the page. | G5: Cart keeps its contents. | H5: Pass | I5: Medium | J5: Minor | K5: Le panier survit aux rechargements et à la navigation (localStorage fironova_cart_v1). | L5: [Claude (Cowork) — 27/09/2026]
A6: PA-005 | B6: Checkout | C6: Access checkout | D6: Non-empty cart | E6: — | F6: 1. Click 'Order / Checkout'. | G6: Opens /checkout with shipping form + summary. | H6: Pass | I6: High | J6: Blocker | K6: /checkout : formulaire (contact, livraison, facturation, paiement, attestations) + résumé. | L6: Les champs n'ont pas de <label> associé (lecteur d'écran : 'textbox' sans nom). [Claude (Cowork) — 27/09/2026]
A7: PA-006 | B7: Checkout | C7: Canada address validation (postal code) | D7: Checkout open | E7: — | F7: 1. Enter an invalid Canadian postal code. 2. Validate. | G7: Error 'Invalid Canadian postal code'. | H7: Pass | I7: High | J7: Major | K7: Code postal '12345' → toast 'Code postal canadien invalide'. Le champ le reformate en '123 45'. | L7: Erreur seulement en toast, pas sous le champ. [Claude (Cowork) — 27/09/2026]
A8: PA-007 | B8: Checkout | C8: US address validation (ZIP) | D8: Country = US | E8: — | F8: 1. Enter an invalid ZIP. 2. Validate. | G8: Error 'Invalid ZIP code'. | H8: N/A | I8: Medium | J8: Minor | K8: Le sélecteur Pays ne propose que Canada : validation ZIP US impossible à tester. | L8: Si les US ne sont pas desservis, retirer 'PROVINCE / ÉTAT' et 'CODE POSTAL / ZIP' des libellés. [Claude (Cowork) — 27/09/2026]
A9: PA-008 | B9: Checkout | C9: Required fields | D9: Checkout open | E9: — | F9: 1. Leave fields empty. 2. Validate. | G9: Clear errors on each required field (Name, Address, City, Province, Postal code, Country). | H9: Fail | I9: High | J9: Major | K9: Bouton actif dès que courriel + cases cochées, même avec l'adresse vide. Au clic, UNE seule erreur à la fois en toast ('Nom est requis' alors que c'est Prénom qui est vide, puis 'Adresse est requis'). | L9: Attendu : une erreur claire sous chaque champ requis. Accord : 'Adresse est requise'. Le message du bas ne liste que courriel/âge/politique, pas l'adresse. [Claude (Cowork) — 27/09/2026]
A10: PA-009 | B10: Checkout | C10: Address suggestion (Google AVS) | D10: Invalid address rejected by server | E10: — | F10: 1. Submit an invalid address (detail.code = invalid_shipping_address). | G10: Suggested-address dialog shown, without permanently blocking. | H10: To test | I10: Low | J10: Minor
A11: PA-010 | B11: Checkout | C11: Shipping $20 under $200 | D11: Cart < $200 | E11: — | F11: 1. Check the fee summary. | G11: Shipping = $20 CAD. | H11: Pass | I11: High | J11: Major | K11: Panier 69,99 $ → livraison 20,00 $, total 89,99 $. | L11: [Claude (Cowork) — 27/09/2026]
A12: PA-011 | B12: Checkout | C12: Free shipping from $200 | D12: Cart ≥ $200 | E12: — | F12: 1. Check the fee summary. | G12: 'FREE' shipping shown. | H12: Pass | I12: High | J12: Major | K12: Panier 259,98 $ → livraison 'GRATUITE', total 259,98 $. | L12: [Claude (Cowork) — 27/09/2026]
A13: PA-012 | B13: Checkout | C13: 'Only $X away from free shipping' hint | D13: Cart below threshold | E13: — | F13: 1. Observe the summary. | G13: Message showing remaining amount to reach free shipping. | H13: Pass | I13: Medium | J13: Minor | K13: 'LIVRAISON GRATUITE DÈS 200$ : PLUS QUE 130.01$' (calcul correct). | L13: Format canadien-français : '130,01 $'. Tous les prix sont en '$69.99' même en FR. [Claude (Cowork) — 27/09/2026]
A14: PA-013 | B14: Checkout | C14: Apply a coupon | D14: Valid coupon exists | E14: — | F14: 1. Enter code. 2. Apply. | G14: Discount line added to summary, total recalculated. | H14: Blocked | I14: High | J14: Major | K14: Aucun code promo valide connu. | L14: À faire après création d'un coupon en admin (CP-001). [Claude (Cowork) — 27/09/2026]
A15: PA-014 | B15: Checkout | C15: Invalid / expired coupon | D15: Non-existent coupon | E15: — | F15: 1. Enter a wrong code. 2. Apply. | G15: Clear error message, no discount applied. | H15: Pass | I15: Medium | J15: Minor | K15: 'FAUXCODE99' → toast d'erreur, aucune remise appliquée. | L15: Le message est en ANGLAIS ('Invalid coupon code') alors que le site est en FR. Le champ code promo n'a pas de libellé. [Claude (Cowork) — 27/09/2026]
A16: PA-015 | B16: Checkout | C16: Remove an applied coupon | D16: Coupon applied | E16: — | F16: 1. Click 'Remove'. | G16: Discount removed, total back to normal. | H16: Blocked | I16: Medium | J16: Minor | K16: Dépend de PA-013. | L16: [Claude (Cowork) — 27/09/2026]
A17: PA-016 | B17: Checkout | C17: Confirmation checkboxes (19+, research, T&C) | D17: Checkout filled | E17: — | F17: 1. Leave boxes unchecked. 2. Validate. | G17: Validation blocked with acceptance-required message. | H17: Pass | I17: High | J17: Blocker | K17: Cases non cochées : bouton désactivé + 'Confirmez votre âge et l'usage recherche. Acceptez la politique.' | L17: Deux cases seulement (âge/RUO combinés + politique), conforme au redesign. [Claude (Cowork) — 27/09/2026]
A18: PA-017 | B18: Checkout | C18: Payment method choice (Interac / crypto) | D18: Checkout filled | E18: — | F18: 1. Toggle Interac ↔ NOWPayments. | G18: Payment mode updates (instructions vs crypto widget). | H18: Pass | I18: High | J18: Major | K18: Interac ↔ Crypto : état CHOISI/CHOISIR et texte mis à jour ('instructions de virement Interac…' / 'Le paiement en USDC s'affichera sur la page suivante…'). | L18: [Claude (Cowork) — 27/09/2026]
A19: PA-018 | B19: Checkout | C19: Checkout draft preserved (login) | D19: Checkout started, then login | E19: Client1 | F19: 1. Fill partially. 2. Log in mid-flow. | G19: Entered data (email, payment method, address) is restored. | H19: Blocked | I19: Low | J19: Minor | K19: Nécessite une connexion client. Partiel : le brouillon (courriel, adresse, mode de paiement) est restauré après rechargement ; les cases à cocher ne le sont pas (voulu). Le brouillon est vidé après la commande. | L19: [Claude (Cowork) — 27/09/2026]
A20: PA-019 | B20: Checkout | C20: Idempotency (double click) | D20: Checkout ready | E20: — | F20: 1. Double-click 'Confirm'. | G20: A single order is created (no duplicate). | H20: Pass | I20: High | J20: Blocker | K20: Double-clic réel sur 'Procéder au paiement' → UN SEUL POST /api/checkout, une seule commande (FN-260927-F5FE5701). | L20: SÉCURITÉ OK : prix d'Épitalon modifié à 1,00 $ dans localStorage → la commande a été facturée au vrai prix (259,98 $). Mais le checkout affichait 210,99 $ avant validation : le client voit un total différent de celui facturé. Le résumé devrait recharger les prix depuis l'API. [Claude (Cowork) — 27/09/2026]

Sheet 4. Payments & Confirmation
A1: ID | B1: Module | C1: Test case / Scenario | D1: Preconditions / Data | E1: Account required | F1: Steps | G1: Expected result | H1: Status | I1: Priority | J1: Severity | K1: Actual result | L1: Comments
A2: PM-001 | B2: Confirmation | C2: Access confirmation page | D2: Order placed | E2: — | F2: 1. After checkout, stay on /order/:id. | G2: Order number + summary displayed. | H2: Pass | I2: High | J2: Blocker | K2: /order/:id : 'Commande reçue', numéro FN-260927-F5FE5701, date, articles et totaux. | L2: Titre de l'onglet en anglais ('Order : Fironova'). [Claude (Cowork) — 27/09/2026]
A3: PM-002 | B3: Confirmation | C3: Interac instructions | D3: Order paid via Interac | E3: — | F3: 1. Observe the Interac section. | G3: Recipient, CAD amount, reference, security question/answer visible. | H3: Fail | I3: High | J3: Major | K3: Destinataire orders@fironova.com, montant 259,98 $ CAD, référence = numéro de commande : OK. | L3: QUESTION DE SÉCURITÉ en anglais ('What is the brand name? (lowercase)') et RÉPONSE = 'nordpep' (ancienne marque !). À remplacer (ex. réponse 'fironova') et traduire la question. [Claude (Cowork) — 27/09/2026]
A4: PM-003 | B4: Confirmation | C4: NOWPayments crypto widget | D4: Order paid via crypto | E4: — | F4: 1. Observe the crypto section. | G4: NOWPayments iframe widget with iid (invoice_id) + exact CAD amount. | H4: Pass | I4: High | J4: Major | K4: Iframe nowpayments.io/embeds/payment-widget avec iid, montant 50,00 $ CAD (≈ 37,166492 USDC). Lien de secours 'Ouvrir la page de paiement'. | L4: Grand espace blanc vide dans le module (cosmétique, côté NOWPayments). [Claude (Cowork) — 27/09/2026]
A5: PM-004 | B5: Confirmation | C5: 'Key things to note' section (crypto) | D5: Crypto order | E5: — | F5: 1. Read under the widget. | G5: 4 bilingual bullets (stay on page, exact amount, minimum, non-refundable). | H5: Pass | I5: Low | J5: Minor | K5: 4 points FR sous le module (rester sur la page, montant exact, minimum, non remboursable). | L5: [Claude (Cowork) — 27/09/2026]
A6: PM-005 | B6: Confirmation | C6: Payment-required banner (per-order delay) | D6: Unpaid order | E6: — | F6: 1. Observe the red banner. | G6: 'Payment required within X' where X is the order's REAL delay (e.g. '30 minutes' in production). Countdown tick: 15 s. | H6: Pass | I6: High | J6: Major | K6: Bandeau 'IL VOUS RESTE 1 H 59 MIN POUR PAYER' + 'Passé ce délai, la commande est annulée automatiquement.' Délai réel = 2 h (mode test). | L6: Bandeau orange et non rouge. Format '2 H 0 MIN' → préférer '2 h 00 min'. [Claude (Cowork) — 27/09/2026]
A7: PM-006 | B7: Confirmation | C7: Live countdown | D7: Unpaid order | E7: — | F7: 1. Wait 15 s. 2. Observe. | G7: 'You have X h Y min left' updates; 'Expired' after deadline. | H7: Pass | I7: Medium | J7: Minor | K7: Décompte passé de 1 h 59 à 1 h 58 en ~80 s sans rechargement. | L7: 'Expiré' non vérifié (2 h d'attente). [Claude (Cowork) — 27/09/2026]
A8: PM-007 | B8: Confirmation | C8: Instructions hidden after payment | D8: Paid order | E8: — | F8: 1. Open confirmation once paid. | G8: Crypto widget and Interac instructions hidden; green 'Payment received' banner. | H8: To test | I8: High | J8: Major
A9: PM-008 | B9: Confirmation | C9: Crypto status polling (20 s) | D9: Pending crypto order | E9: — | F9: 1. Leave the page open. | G9: NOWPayments status re-polled every 20 s; 'paid' only on status 'finished'. | H9: Pass | I9: Medium | J9: Major | K9: GET /api/payments/crypto/status/:id toutes les ~20 s (2 appels en 40 s). | L9: L'appel sans le jeton invité renvoie 403 (bonne protection). [Claude (Cowork) — 27/09/2026]
A10: PM-009 | B10: Webhook | C10: NOWPayments IPN webhook (HMAC) | D10: Webhook + secret configured | E10: — | F10: 1. Simulate a signed IPN (status finished). | G10: Order → 'paid' (idempotent), system note + email sent. | H10: To test | I10: High | J10: Blocker
A11: PM-010 | B11: Webhook | C11: Invalid IPN (bad signature) | D11: IPN secret configured | E11: — | F11: 1. Send a badly signed IPN. | G11: Rejected 401/400, no order marked paid. | H11: Blocked | I11: High | J11: Blocker | K11: Chemin du webhook IPN inconnu (6 chemins testés → 404). | L11: Donner l'URL du webhook pour tester une signature invalide. [Claude (Cowork) — 27/09/2026]
A12: PM-011 | B12: Payment | C12: Auto-cancel unpaid order (per-order delay) | D12: Unpaid order + watchdog | E12: — | F12: 1. Wait for deadline (or force watchdog). | G12: Order → cancelled, system note, stock restocked. | H12: To test | I12: High | J12: Major
A13: PM-012 | B13: Payment | C13: Late Interac payment (cancelled order) | D13: Cancelled order | E13: — | F13: 1. Let an e-Transfer arrive after cancellation. | G13: '⚠️ LATE PAYMENT' note + late_payment flags set (idempotent). | H13: To test | I13: Medium | J13: Major
A14: PM-013 | B14: Invoice | C14: Invoice PDF download | D14: Paid order | E14: — | F14: 1. Download invoice (admin). | G14: ReportLab PDF with logo, items table, totals, regulatory footer. | H14: To test | I14: Medium | J14: Minor
A15: PM-014 | B15: Confirmation | C15: Production banner: 30 minutes | D15: Unpaid order, TTL 0.5 h (production) | E15: — | F15: 1. Open /order/:id for an order awaiting payment. | G15: 'Payment required within 30 minutes' + countdown (15 s tick). | H15: N/A | I15: High | J15: Major | K15: Environnement de test : délai 2 h. Le texte 30 minutes ne peut être vérifié qu'en production. | L15: [Claude (Cowork) — 27/09/2026]

Sheet 5. Account & Authentication
A1: ID | B1: Module | C1: Test case / Scenario | D1: Preconditions / Data | E1: Account required | F1: Steps | G1: Expected result | H1: Status | I1: Priority | J1: Severity | K1: Actual result | L1: Comments
A2: AU-001 | B2: Signup | C2: Account creation | D2: No account | E2: New client | F2: 1. /register. 2. Enter email + password. 3. Submit. | G2: Account created, session open, redirect. | H2: Blocked | I2: High | J2: Blocker | K2: Création de compte : faite par un humain (je n'ai pas le droit de saisir des mots de passe sur un site en ligne). | L2: [Claude (Cowork) — 27/09/2026]
A3: AU-002 | B3: Signup | C3: Email already in use | D3: Existing account | E3: Client1 | F3: 1. Reuse the same email. | G3: Clear 'email already in use' error. | H3: Blocked | I3: Medium | J3: Minor | K3: Idem AU-001. | L3: [Claude (Cowork) — 27/09/2026]
A4: AU-003 | B4: Login | C4: Email + password login | D4: Account created | E4: Client1 | F4: 1. /login. 2. Enter credentials. | G4: Session open (httpOnly cookie), redirect. | H4: Blocked | I4: High | J4: Blocker | K4: Connexion par mot de passe : à faire par Mishka. | L4: [Claude (Cowork) — 27/09/2026]
A5: AU-004 | B5: Login | C5: Wrong password | D5: Account created | E5: Client1 | F5: 1. Enter a wrong password. | G5: Generic error (no info leak). | H5: Blocked | I5: High | J5: Major | K5: Idem. | L5: [Claude (Cowork) — 27/09/2026]
A6: AU-005 | B6: Login | C6: Brute-force lockout (5 attempts) | D6: Account created | E6: Brute-force client | F6: 1. 5 wrong attempts from same IP. | G6: 429 / temporary block; different IP gets 401 (Cloudflare distinction). | H6: Blocked | I6: High | J6: Major | K6: Idem (5 mauvais mots de passe). | L6: [Claude (Cowork) — 27/09/2026]
A7: AU-006 | B7: Login | C7: IP behind Cloudflare (CF-Connecting-IP) | D7: Traffic via CDN | E7: Brute-force client | F7: 1. Attempt several logins. | G7: Rate-limit uses CF-Connecting-IP (not proxy IP). | H7: Blocked | I7: Medium | J7: Minor | K7: Idem. | L7: [Claude (Cowork) — 27/09/2026]
A8: AU-007 | B8: Login | C8: Google OAuth | D8: GOOGLE_CLIENT_ID/secret configured | E8: Google client (OAuth) | F8: 1. Click 'Sign in with Google'. | G8: Account created/attached, same httpOnly session cookie. | H8: Blocked | I8: Medium | J8: Major | K8: OAuth Google : à faire par Mishka. | L8: [Claude (Cowork) — 27/09/2026]
A9: AU-008 | B9: Password | C9: Forgot password | D9: Account created | E9: Client1 | F9: 1. /forgot-password. 2. Enter email. | G9: Reset email sent (Resend). | H9: Pass | I9: Medium | J9: Major | K9: /forgot-password : message générique 'Si un compte existe pour cette adresse… expire dans 30 minutes' (pas de fuite d'info). | L9: Réception du courriel (Resend) non vérifiée : boîte de test requise. [Claude (Cowork) — 27/09/2026]
A10: AU-009 | B10: Password | C10: Password reset | D10: Link received by email | E10: Client1 | F10: 1. Open the link. 2. Choose new password. | G10: Password reset, old one invalidated. | H10: To test | I10: Medium | J10: Major
A11: AU-010 | B11: Login | C11: Magic link | D11: Email sent | E11: Client1 | F11: 1. Click the magic-link. | G11: 1-click login without password, session open. | H11: To test | I11: Medium | J11: Major
A12: AU-011 | B12: Account | C12: Protected /account | D12: Logged out | E12: — | F12: 1. Try to open /account. | G12: Redirected to /login (ProtectedRoute). | H12: Pass | I12: High | J12: Major | K12: /account déconnecté → redirection /login. | L12: /affiliate déconnecté → /login aussi. [Claude (Cowork) — 27/09/2026]
A13: AU-012 | B13: Account | C13: Saved addresses + reuse | D13: Logged-in account | E13: Client1 | F13: 1. Add an address. 2. Reuse it at checkout. | G13: Addresses persisted and selectable at checkout. | H13: To test | I13: Medium | J13: Minor
A14: AU-013 | B14: Account | C14: Order history | D14: Orders placed | E14: Client1 | F14: 1. Open /account. | G14: Order list with visible statuses. | H14: To test | I14: Medium | J14: Minor
A15: AU-014 | B15: Session | C15: Expiry / refresh | D15: Session open | E15: Client1 | F15: 1. Wait ACCESS_TOKEN_MINUTES. 2. Act. | G15: httpOnly refresh cookie renews the session without re-login. | H15: To test | I15: Low | J15: Minor
A16: AU-015 | B16: Newsletter | C16: Signup + double opt-in | D16: Valid email | E16: Newsletter client | F16: 1. Subscribe. 2. Click /newsletter/confirm/:token. | G16: Subscription confirmed after clicking one-time link. | H16: Fail | I16: Low | J16: Minor | K16: Sans case cochée : 'Veuillez confirmer votre consentement…' (OK). Avec case : toast immédiat 'Confirmé : vous êtes inscrit.' | L16: Attendu : double opt-in (message 'vérifiez votre courriel pour confirmer'). Le message affiché laisse croire que l'inscription est confirmée sans clic sur le lien. Vérifier dans la boîte de réception si un lien /newsletter/confirm est bien envoyé. [Claude (Cowork) — 27/09/2026]
A17: AU-016 | B17: Login | C17: Magic link → an affiliate lands on /affiliate (dashboard), not /account | D17: Affiliate account | E17: Affiliate1 | H17: To test

Sheet 6. Legal & Info pages
A1: ID | B1: Module | C1: Test case / Scenario | D1: Preconditions / Data | E1: Account required | F1: Steps | G1: Expected result | H1: Status | I1: Priority | J1: Severity | K1: Actual result | L1: Comments
A2: LE-001 | B2: T&C | C2: Bilingual Terms & Conditions page | D2: Site loaded | E2: — | F2: 1. /compliance. | G2: 17 bilingual FR/EN sections (acceptance, 19+, research use, returns, etc.). | H2: Pass | I2: High | J2: Blocker | K2: /compliance : 17 sections numérotées + Politique d'expédition, en FR et EN (acceptation, 19+, usage, retours…). | L2: [Claude (Cowork) — 27/09/2026]
A3: LE-002 | B3: T&C | C3: Shipping policy section (#shipping) | D3: T&C page | E3: — | F3: 1. Navigate to shipping section. | G3: 7 bilingual subsections ($200 free, 2 pm ET, regional delays, lost parcels). | H3: Pass | I3: High | J3: Major | K3: #shipping : section 'Politique d'expédition' avec 8 sous-titres, livraison gratuite dès 200 $, heure limite 13 h HE (FR) / 1:00 p.m. Eastern (EN). FAQ cohérente (13 h). | L3: Le plan dit '2 pm ET' et '7 sous-sections' : le plan est à mettre à jour (13 h est la règle décidée). [Claude (Cowork) — 27/09/2026]
A4: LE-003 | B4: Privacy | C4: /privacy page | D4: Site loaded | E4: — | F4: 1. /privacy. | G4: 11 bilingual sections, LPRPDE + Law 25 mention. | H4: Pass | I4: Medium | J4: Major | K4: /privacy : 12 sections FR et EN, mentions LPRPDE/PIPEDA et Loi 25 présentes. | L4: Le plan attend 11 sections. [Claude (Cowork) — 27/09/2026]
A5: LE-004 | B5: FAQ | C5: /faq page (accordions) | D5: Site loaded | E5: — | F5: 1. /faq. 2. Expand accordions. | G5: 5 categories, 22 bilingual questions, contact block info@nordpep.ca. | H5: Pass | I5: Medium | J5: Minor | K5: /faq : 5 catégories + bloc contact, 23 questions en accordéon (FR et EN), contact info@fironova.com. | L5: Le plan attend 22 questions et info@nordpep.ca : le plan est obsolète, le site est correct. [Claude (Cowork) — 27/09/2026]
A6: LE-005 | B6: Lab | C6: /lab page (COA) | D6: COA_PAGE_ENABLED=true | E6: — | F6: 1. /lab. | G6: Lab page visible. (If flag off → redirect home.) | H6: Pass | I6: Low | J6: Minor | K6: /lab redirige vers l'accueil (COA_PAGE_ENABLED désactivé). | L6: [Claude (Cowork) — 27/09/2026]
A7: LE-006 | B7: About | C7: /about page | D7: Site loaded | E7: — | F7: 1. /about. | G7: About page loads, bilingual. | H7: Pass | I7: Low | J7: Minor | K7: /about charge en FR et EN. | L7: Contenu très court (~450 caractères) et page introuvable dans la navigation (voir SP-007). [Claude (Cowork) — 27/09/2026]
A8: LE-007 | B8: Compliance | C8: No 'Health Canada / FDA' mention | D8: T&C/FAQ pages | E8: — | F8: 1. Browse T&C + FAQ. | G8: No Health Canada/FDA mention; neutral 'research use only' wording. | H8: Pass | I8: High | J8: Blocker | K8: Aucune mention 'Health Canada', 'Santé Canada' ou 'FDA' dans les CG, la FAQ ni la politique de confidentialité (FR et EN). | L8: [Claude (Cowork) — 27/09/2026]
A9: LE-008 | B9: Compliance | C9: 19+ restriction everywhere | D9: Whole site | E9: — | F9: 1. Check header, footer, invoice, T&C. | G9: 19+ and 'research use only' notices present everywhere. | H9: Pass | I9: High | J9: Blocker | K9: 19+ et 'usage recherche uniquement' dans le bandeau du haut, le footer ('Âge vérifié 19+'), l'AgeGate et la section 03 des CG. | L9: Facture PDF non vérifiée (admin requis). [Claude (Cowork) — 27/09/2026]

Sheet 7. Affiliates (client)
A1: ID | B1: Module | C1: Test case / Scenario | D1: Preconditions / Data | E1: Account required | F1: Steps | G1: Expected result | H1: Status | I1: Priority | J1: Severity | K1: Actual result | L1: Comments
A2: AF-001 | B2: Invitation | C2: 1-click magic-link activation (/affiliate/join) | D2: Invitation email received | E2: Affiliate3 | F2: 1. Open the invitation link. | G2: Passwordless account created, affiliate activated, JWT set, redirect /affiliate in ~1.2 s. | H2: To test | I2: High | J2: Major
A3: AF-002 | B3: Program | C3: Program page (valid token) | D3: Valid invitation token | E3: Affiliate3 | F3: 1. /affiliate/programme. | G3: Program shows only with a valid token. | H3: To test | I3: Medium | J3: Minor
A4: AF-003 | B4: Terms | C4: /affiliate/terms page (public) | D4: No account | E4: — | F4: 1. /affiliate/terms. | G4: Terms publicly readable (before acceptance). | H4: Pass | I4: Medium | J4: Minor | K4: /affiliate/terms lisible sans compte, FR et EN. | L4: [Claude (Cowork) — 27/09/2026]
A5: AF-004 | B5: Dashboard | C5: /affiliate access (protected) | D5: Affiliate logged in | E5: Affiliate1 | F5: 1. /affiliate. | G5: Affiliate dashboard (sales, commissions, top products). | H5: To test | I5: High | J5: Major
A6: AF-005 | B6: Dashboard | C6: Top products (rank, qty, revenue) | D6: Affiliate with sales | E6: Affiliate1 | F6: 1. Open the 'Top products' widget. | G6: Rank 1/2/3 badges + quantity sold + revenue, FR/EN pluralization. | H6: To test | I6: Medium | J6: Minor
A7: AF-006 | B7: Dashboard | C7: Featured products fallback | D7: Affiliate with no sale | E7: Affiliate2 | F7: 1. Open dashboard. | G7: Falls back to /products?featured=true if no sales. | H7: To test | I7: Low | J7: Minor
A8: AF-007 | B8: Attribution | C8: Referral link ?ref=<code> | D8: Active affiliate code | E8: Client2 (+ Affiliate1 code) | F8: 1. Open site with ?ref=CODE. 2. Order. | G8: Attribution recorded; active alias also accepted. | H8: To test | I8: High | J8: Major
A9: AF-008 | B9: Settings | C9: Payout config USDT/USDC ERC-20 | D9: Affiliate logged in | E9: Affiliate1 | F9: 1. Enter an ERC-20 address. | G9: EIP-55 checksum validation (success/warning badge), currency limited to USDT/USDC. | H9: To test | I9: Medium | J9: Major
A10: AF-009 | B10: Settings | C10: Invalid Ethereum address | D10: Affiliate logged in | E10: Affiliate1 | F10: 1. Enter an invalid address. | G10: Clear inline error, not saved. | H10: To test | I10: Medium | J10: Minor
A11: AF-010 | B11: FAQ | C11: /affiliate/faq access (protected) | D11: Affiliate account | E11: Affiliate1 | F11: 1. /affiliate/faq. | G11: FAQ accessible to affiliates only. | H11: To test | I11: Low | J11: Minor
A12: AF-011 | B12: Dashboard | C12: Notification bell : badge, list, dismiss one / all | D12: Affiliate logged in, at least one notification | E12: Affiliate1 | H12: To test
A13: AF-012 | B13: Dashboard | C13: Notification types : message (support reply) / palier (tier up) / paiement (payout setup) | D13: Affiliate account | E13: Affiliate1 | H13: To test
A14: AF-013 | B14: Dashboard | C14: Account menu : customer account link, dark mode, logout | D14: Affiliate logged in | E14: Affiliate1 | H14: To test
A15: AF-014 | B15: Dashboard | C15: FAQ tab in the menu (after Help) + menu also on the FAQ page | D15: Affiliate logged in | E15: Affiliate1 | H15: To test
A16: AF-015 | B16: Dashboard | C16: Two-moment card : 'Vos ventes' (12 months) and 'Vos ventes au 1er' (forecast) with the two amounts below the forecast | D16: Affiliate with sales | E16: Affiliate1 | H16: To test
A17: AF-016 | B17: Dashboard | C17: Chart anchored to the tier rhythm : a month at 2x the rhythm is capped with a chevron, never a new scale | D17: Affiliate with sales | E17: Affiliate1 | H17: To test
A18: AF-017 | B18: Auth | C18: Magic link redirects an affiliate to /affiliate (no specific target) | D18: Affiliate logs in | E18: Affiliate1 | H18: To test
A19: AF-018 | B19: Dashboard | C19: Invitation wall for a logged-in NON-affiliate : 'signed in but not part of the program' + account button | D19: Customer logged in, opens /affiliate | E19: Client1 | H19: To test
A20: AF-019 | B20: Settings | C20: Payout-setup reminder : bell notification + email ~5 days before month end | D20: Commissions >= $25 threshold, no payout address | E20: Payout affiliate | H20: To test
A21: AF-020 | B21: Dashboard | C21: Dark mode : card stays navy, amounts visible, no white panels | D21: Affiliate logged in, dark mode on | E21: Affiliate1 | H21: To test
A22: AF-021 | B22: Dashboard | C22: Mobile (360-768 px) : card full width, sections stacked, full-size chart | D22: Affiliate logged in, phone | E22: Affiliate1 | H22: To test

Sheet 8. Admin — General & Dashboard
A1: ID | B1: Module | C1: Test case / Scenario | D1: Preconditions / Data | E1: Account required | F1: Steps | G1: Expected result | H1: Status | I1: Priority | J1: Severity | K1: Actual result | L1: Comments
A2: AD-001 | B2: Access | C2: Secret admin path | D2: Admin account | E2: Admin | F2: 1. /ops-portal-fn7k2q. | G2: Admin portal loads (admin gate + protected route). | H2: To test | I2: High | J2: Blocker
A3: AD-002 | B3: Access | C3: /admin and /ops aliases redirect | D3: Admin account | E3: Admin | F3: 1. /admin and /ops. | G3: Redirect to the secret admin path. | H3: To test | I3: Low | J3: Minor
A4: AD-003 | B4: Access | C4: Non-admin denied | D4: Customer account | E4: Client1 | F4: 1. Try to open admin. | G4: Access denied / redirected (AdminGate). | H4: To test | I4: High | J4: Blocker
A5: AD-004 | B5: Layout | C5: Grouped sidebar (Sales/Catalog/Fulfillment/Growth/System) | D5: Admin logged in | E5: Admin | F5: 1. Check the sidebar. | G5: Groups/items visible by permission, signal badges. | H5: To test | I5: High | J5: Major
A6: AD-005 | B6: Layout | C6: Collapsible menu + persistence | D6: Admin logged in | E6: Admin | F6: 1. Collapse menu. 2. Reload. | G6: Menu stays collapsed (localStorage). | H6: To test | I6: Low | J6: Minor
A7: AD-006 | B7: Layout | C7: Search palette Ctrl+K / '/' | D7: Admin logged in | E7: Admin | F7: 1. Ctrl+K then '/'. | G7: Search palette opens; '/' does not steal keystrokes in a field. | H7: To test | I7: Low | J7: Minor
A8: AD-007 | B8: Layout | C8: Breadcrumb + avatar | D8: Admin logged in | E8: Admin | F8: 1. Navigate between screens. | G8: Breadcrumb reflects current screen, avatar with initials. | H8: To test | I8: Low | J8: Minor
A9: AD-008 | B9: Dashboard | C9: KPI cards (Revenue, Orders, Customers, Products) | D9: Admin logged in | E9: Admin | F9: 1. Open dashboard. | G9: 4 KPI cards with consistent values + low-stock flag. | H9: To test | I9: High | J9: Major
A10: AD-009 | B10: Dashboard | C10: 30-day revenue chart + top products | D10: Admin logged in | E10: Admin | F10: 1. Check charts. | G10: 30-day bar chart, top products, recent orders shown. | H10: To test | I10: Medium | J10: Minor
A11: AD-010 | B11: Notifications | C11: Bell + alert counters | D11: Admin logged in, active signals | E11: Admin | F11: 1. Open bell. 2. Handle an item. | G11: Counters refreshed (60 s, screen change, tab return). | H11: To test | I11: Medium | J11: Minor
A12: AD-011 | B12: Notifications | C12: Low-stock badge on Products | D12: Stock below threshold | E12: Admin | F12: 1. Observe Products entry. | G12: Red badge with low-stock alert count. | H12: To test | I12: Medium | J12: Minor
A13: AD-012 | B13: Dashboard | C13: Pending manifest alert | D13: pending_manifest > 0 | E13: Admin | F13: 1. Observe the red banner. | G13: 'X label(s) not transmitted' banner + Dispatch link. | H13: To test | I13: Medium | J13: Minor
A14: AD-013 | B14: Dark mode | C14: Admin dark theme | D14: Admin logged in | E14: Admin | F14: 1. Toggle theme. | G14: Admin UI in readable dark mode. | H14: To test | I14: Low | J14: Minor

Sheet 9. Orders & Fulfillment
A1: ID | B1: Module | C1: Test case / Scenario | D1: Preconditions / Data | E1: Account required | F1: Steps | G1: Expected result | H1: Status | I1: Priority | J1: Severity | K1: Actual result | L1: Comments
A2: CO-001 | B2: Orders | C2: List + filters | D2: Existing orders | E2: Admin | F2: 1. Open Orders. 2. Filter (search, payment, fulfillment). | G2: List filtered correctly. | H2: To test | I2: High | J2: Major
A3: CO-002 | B3: Orders | C3: CSV export | D3: Existing orders | E3: Admin | F3: 1. Click 'Export CSV'. | G3: orders.csv downloaded with correct data. | H3: To test | I3: Medium | J3: Minor
A4: CO-003 | B4: Orders | C4: Order detail drawer | D4: Existing order | E4: Admin | F4: 1. Click an order. | G4: Drawer with items, statuses, notes, actions. | H4: To test | I4: High | J4: Major
A5: CO-004 | B5: Orders | C5: Confirm payment (Interac/crypto) | D5: Order awaiting_etransfer/crypto | E5: Admin | F5: 1. Click 'Confirm payment'. | G5: Order → paid + processing, email sent, coupon usage incremented. | H5: To test | I5: High | J5: Blocker
A6: CO-005 | B6: Orders | C6: Internal notes | D6: Order open | E6: Admin | F6: 1. Add a note. | G6: Note added to internal thread, persisted. | H6: To test | I6: Medium | J6: Minor
A7: CO-006 | B7: Orders | C7: Carrier + tracking entry | D7: Paid order | E7: Admin | F7: 1. Enter carrier + tracking. 2. Save. | G7: Auto-marks as 'shipped'. | H7: To test | I7: High | J7: Major
A8: CO-007 | B8: Orders | C8: Invoice PDF from drawer | D8: Paid order | E8: Admin | F8: 1. Click 'Invoice PDF'. | G8: PDF downloaded (logo, items, totals, disclaimer). | H8: To test | I8: Medium | J8: Minor
A9: CO-008 | B9: Orders | C9: Manual cancellation | D9: Active order | E9: Admin | F9: 1. Cancel the order. | G9: Stock restocked, coupon decremented (coupon_counted flag), audit cancelled_at/reason. | H9: To test | I9: High | J9: Major
A10: CO-009 | B10: Orders | C10: Reopen a cancelled order | D10: Cancelled order | E10: Admin | F10: 1. Click 'Reopen'. | G10: Stock re-decremented, coupon restored (usage_limit), status restored. | H10: To test | I10: High | J10: Major
A11: CO-010 | B11: Orders | C11: Reopen + mark paid (late payment) | D11: Order late_payment_flagged | E11: Admin | F11: 1. Click 'Reopen + mark paid'. | G11: Order reopened and confirmed paid. | H11: To test | I11: Medium | J11: Major
A12: CO-011 | B12: Shipping | C12: Zones & methods (CRUD) | D12: Admin logged in | E12: Admin | F12: 1. Create/edit a zone + method. | G12: Shipping zones/methods CRUD works. | H12: To test | I12: Medium | J12: Minor
A13: CO-012 | B13: Shipping | C13: Packaging / boxes | D13: Admin logged in | E13: Admin | F13: 1. Manage packaging. | G13: Packaging CRUD works. | H13: To test | I13: Low | J13: Minor
... A18: CO-017 | B18: Refunds | C18: Refund management | D18: Paid order | E18: Admin | F18: 1. Initiate a refund. | G18: Refund recorded, status refunded. | H18: To test | I18: Medium | J18: Major
A19: CO-018 | B19: Shipping | C19: Same-day dispatch cutoff at 1:00 p.m. ET | D19: Two orders paid on the same business day | E19: — | F19: 1. Pay the first before 1:00 p.m. ET. 2. Pay the second after 1:00 p.m. ET. | G19: The first ships the same day; the second leaves on the next business day. | H19: To test | I19: High | J19: Major | L19: ORDER_CUTOFF_HOUR=13; the pages now announce 1:00 p.m.

Sheet 10. Admin — Products & Stock
A1: ID | B1: Module | C1: Test case / Scenario | D1: Preconditions / Data | E1: Account required | F1: Steps | G1: Expected result | H1: Status | I1: Priority | J1: Severity | K1: Actual result | L1: Comments
A2: PR-001 | B2: Products | C2: Product list (image, stock, COA, featured) | D2: Seeded products | E2: Admin | F2: 1. Open Products. | G2: Full table with stock indicators and COA/Featured badges. | H2: To test | I2: High | J2: Major
A3: PR-002 | B3: Products | C3: Product editor (Basic/Stock/COA/Visibility) | D3: Existing product | E3: Admin | F3: 1. Open editor (drawer). 2. Edit a field. | G3: Changes saved and reflected on the storefront. | H3: To test | I3: High | J3: Major
A4: PR-003 | B4: Products | C4: CSV export | D4: Existing products | E4: Admin | F4: 1. Click 'Export CSV'. | G4: products.csv downloaded. | H4: To test | I4: Low | J4: Minor
A5: PR-004 | B5: Stock | C5: Stock adjustment (absolute value) | D5: Existing product | E5: Admin | F5: 1. Edit stock in the editor. | G5: Stock updated, stock_movements audit recorded. | H5: To test | I5: High | J5: Major
A6: PR-005 | B6: Stock | C6: Quick Restock (+N) modal | D6: Existing product | E6: Admin | F6: 1. 'PackagePlus' button. 2. +10/+25/+50/+100 or custom. 3. Confirm. | G6: Stock incremented atomically, live totals, audit (admin_email, reason). | H6: To test | I6: High | J6: Major
A7: PR-006 | B7: Stock | C7: Multi-variant restock | D7: Product with variants | E7: Admin | F7: 1. Restock several variants. | G7: Each variant updated, applied[]/skipped[] correct. | H7: To test | I7: Medium | J7: Minor
A8: PR-007 | B8: Stock | C8: Reject quantity <= 0 | D8: Existing product | E8: Admin | F8: 1. Enter 0 or negative via API. | G8: 422 Pydantic, no movement. | H8: To test | I8: Medium | J8: Minor
A9: PR-008 | B9: Stock | C9: Remove stock (-N) / negative adjustment | D9: Product with stock | E9: Admin | F9: 1. Switch to REMOVE mode. 2. -10. 3. Confirm. | G9: Stock decremented, movement type 'adjustment', refused if insufficient. | H9: To test | I9: High | J9: Major
A10: PR-009 | B10: Stock | C10: Atomic guard (insufficient_stock) | D10: Delta > current stock | E10: Admin | F10: 1. Try -9999. | G10: Refused 'insufficient_stock', applied=0. | H10: To test | I10: Medium | J10: Minor
A11: PR-010 | B11: Stock | C11: Bulk Restock CSV (multi-product) | D11: Prepared CSV file | E11: Admin | F11: 1. 'BULK RESTOCK CSV'. 2. Upload. 3. Preview + validate. | G11: applied/failed KPIs, typed rejections (product/variant not found, insufficient). | H11: To test | I11: Medium | J11: Major
A12: PR-011 | B12: Stock | C12: Movement history (stock-history) | D12: Existing movements | E12: Admin | F12: 1. 'VIEW HISTORY'. | G12: Last 50 movements (date, variant, delta, before→after, admin, reason). | H12: To test | I12: Low | J12: Minor
A13: PR-012 | B13: Alerts | C13: Automatic low-stock alert | D13: Stock drops below threshold | E13: Admin | F13: 1. Restock below threshold. | G13: Admin 'Low stock' email + low_stock_alerts row (active=true). | H13: To test | I13: Medium | J13: Major
... A17: PR-016 | B17: Menus | C17: Menu management | D17: Admin logged in | E17: Admin | F17: 1. Edit the header menu. | G17: Menu updated on the storefront. | H17: To test | I17: Low | J17: Minor

Sheet 11. Admin — Coupons & Customers
A1: ID | B1: Module | C1: Test case / Scenario | D1: Preconditions / Data | E1: Account required | F1: Steps | G1: Expected result | H1: Status | I1: Priority | J1: Severity | K1: Actual result | L1: Comments
A2: CP-001 | B2: Coupons | C2: Create coupon (% and fixed) | D2: Admin logged in | E2: Admin | F2: 1. Create a % coupon then a fixed-amount coupon. | G2: Coupons created with code, min_subtotal, usage_limit, expires_at. | H2: To test | I2: High | J2: Major
A3: CP-002 | B3: Coupons | C3: Edit / delete | D3: Existing coupon | E3: Admin | F3: 1. Edit. 2. Delete. | G3: Updates applied, deletion effective. | H3: To test | I3: Medium | J3: Minor
A4: CP-003 | B4: Coupons | C4: Coupon validation (POST validate) | D4: Active coupon | E4: Admin | F4: 1. Validate a code at checkout. | G4: Coupon valid, discount computed. | H4: To test | I4: High | J4: Major
A5: CP-004 | B5: Coupons | C5: Usage limit / expiry | D5: Limited coupon | E5: Admin | F5: 1. Exhaust the limit or pass expiry. | G5: Coupon refused with clear message. | H5: To test | I5: Medium | J5: Major
A6: CP-005 | B6: Coupons | C6: Auto usage increment | D6: Used coupon | E6: Admin | F6: 1. Place an order with coupon. | G6: usage_count incremented automatically. | H6: To test | I6: Medium | J6: Minor
A7: CP-006 | B7: Customers | C7: Customer list | D7: Existing customers | E7: Admin | F7: 1. Open Customers. | G7: Customer list with info. | H7: To test | I7: Medium | J7: Minor

Sheet 12. Affiliates & Payouts
A1: ID | B1: Module | C1: Test case / Scenario | D1: Preconditions / Data | E1: Account required | F1: Steps | G1: Expected result | H1: Status | I1: Priority | J1: Severity | K1: Actual result | L1: Comments
A2: AF-101 | B2: Affiliates | C2: Individual invitation (first/last/company) | D2: Admin logged in | E2: Admin | F2: 1. Invite an affiliate. | G2: Account created, Resend email sent, auto FN+6 code. | H2: To test | I2: High | J2: Major
A3: AF-102 | B3: Affiliates | C3: Bulk invite CSV (drag & drop) | D3: CSV with rows | E3: Admin | F3: 1. 'Bulk invite'. 2. Upload CSV (first_name,last_name,company,email,discount_percent). | G3: Preview + Sent/Skipped/Failed KPIs + CSV download of codes. | H3: To test | I3: Medium | J3: Major
A4: AF-103 | B4: Affiliates | C4: Invalid row rejected without breaking batch | D4: CSV with nameless row | E4: Admin | F4: 1. Upload a CSV with a nameless row. | G4: Row rejected in failed[] with clear message, rest processed. | H4: To test | I4: Medium | J4: Minor
A5: AF-104 | B5: Affiliates | C5: Code generation v2 (BASE + %) | D5: Affiliate with % | E5: Admin | F5: 1. Activate an affiliate at 15%. | G5: Code like GYMPRO15 (company) or MARIE15 (first name), anti-collision. | H5: To test | I5: Medium | J5: Minor
A6: AF-105 | B6: Affiliates | C6: Aliases (percent rename) | D6: Affiliate with code | E6: Admin | F6: 1. Change coupon_percent. | G6: Code regenerated, old one archived in aliases[] (active), old coupon disabled. | H6: To test | I6: Medium | J6: Major
A7: AF-106 | B7: Affiliates | C7: Toggle alias active/inactive | D7: Affiliate with aliases | E7: Admin | F7: 1. Toggle an alias. | G7: Alias enabled/disabled, ?ref= accepts active alias. | H7: To test | I7: Low | J7: Minor
A8: AF-107 | B8: Affiliates | C8: Payout settings (USDT/USDC ERC-20) | D8: Invited affiliate | E8: Admin | F8: 1. Configure an ERC-20 address. | G8: Address canonicalized to EIP-55 checksum, currency validated. | H8: To test | I8: Medium | J8: Major
A9: AF-108 | B9: Payouts | C9: Payout generation (period) | D9: Attributed sales | E9: Admin | F9: 1. Run generation (force-run / scheduler). | G9: Payouts created for the period, minimum threshold respected ($25 CAD). | H9: To test | I9: High | J9: Major
A10: AF-109 | B10: Payouts | C10: Minimum threshold (defer below) | D10: Commissions < $25 | E10: Admin | F10: 1. Generate payouts. | G10: No row created, deferral + bilingual email sent (idempotent). | H10: To test | I10: Medium | J10: Major
A11: AF-110 | B11: Payouts | C11: FX CAD→USD rate (Bank of Canada) | D11: Payouts generated | E11: Admin | F11: 1. Check columns. | G11: BoC FX shown (rate + source), USD amount ≈ 1:1 USDT. | H11: To test | I11: Medium | J11: Minor
A12: AF-111 | B12: Payouts | C12: Batch → NOWPayments (OTP) | D12: Payouts ready + NOWPayments configured | E12: Admin | F12: 1. Select. 2. 'Batch'. 3. OTP. | G12: Mass payouts sent, status processing + np_batch_id. | H12: To test | I12: Medium | J12: Major
A13: AF-112 | B13: Payouts | C13: NOWPayments CSV template export | D13: Payouts ready/queued | E13: Admin | F13: 1. 'Export NOWPayments'. | G13: CSV in official template (Ticker, Wallet, Amount 6 decimals). | H13: To test | I13: Medium | J13: Major
A14: AF-113 | B14: Payouts | C14: Payout webhook → paid | D14: Payout processing | E14: Admin | F14: 1. Simulate webhook. | G14: Payout confirmed → paid. | H14: To test | I14: Medium | J14: Major

Sheet 13. Admin — System
A1: ID | B1: Module | C1: Test case / Scenario | D1: Preconditions / Data | E1: Account required | F1: Steps | G1: Expected result | H1: Status | I1: Priority | J1: Severity | K1: Actual result | L1: Comments
A2: SY-001 | B2: Team | C2: Staff management + permissions | D2: Admin logged in | E2: Admin | F2: 1. Create a staff account. 2. Restrict permissions. | G2: Staff created, access restricted by permissions (areas). | H2: To test | I2: High | J2: Major
A3: SY-002 | B3: Team | C3: Staff invitation (staff-accept) | D3: Invitation email | E3: Staff | F3: 1. Open /staff-accept. | G3: Member accepts and activates. | H3: To test | I3: Low | J3: Minor
A4: SY-003 | B4: Log | C4: Activity log (audit) | D4: Actions performed | E4: Admin | F4: 1. Open the Log. | G4: Actions traced (admin, date, detail). | H4: To test | I4: Medium | J4: Minor
A5: SY-004 | B5: SEO | C5: SEO editing | D5: Admin logged in | E5: Admin | F5: 1. Edit SEO fields. | G5: Save and readback correct. | H5: To test | I5: Low | J5: Minor
A6: SY-005 | B6: Emails | C6: Email catalog / templates | D6: Admin logged in | E6: Admin | F6: 1. Browse templates. | G6: Templates listed and editable. | H6: To test | I6: Low | J6: Minor
A7: SY-006 | B7: Outbox | C7: Email outbox | D7: Emails queued | E7: Admin | F7: 1. Open the Outbox. | G7: Per-status stats, oldest age, janitor config exposed. | H7: To test | I7: Medium | J7: Minor
A8: SY-007 | B8: Outbox | C8: Manual requeue | D8: Failed/stuck emails | E8: Admin | F8: 1. 'Requeue' (scope). | G8: Emails retried (requeued_by: admin). | H8: To test | I8: Low | J8: Minor
A9: SY-008 | B9: Trash | C9: Trash management | D9: Deleted items | E9: Admin | F9: 1. Open Trash. 2. Restore/delete. | G9: Restore and purge work. | H9: To test | I9: Low | J9: Minor
A10: SY-009 | B10: Tickets | C10: Customer & affiliate tickets | D10: Existing tickets | E10: Admin | F10: 1. Open tickets. | G10: Display and reply work. | H10: To test | I10: Low | J10: Minor
A11: SY-010 | B11: Subscribers | C11: Newsletter subscribers list | D11: Existing subscribers | E11: Admin | F11: 1. Open Subscribers. | G11: Subscriber list displayed. | H11: To test | I11: Low | J11: Minor

Sheet 14. Non-functional
A1: ID | B1: Module | C1: Test case / Scenario | D1: Preconditions / Data | E1: Account required | F1: Steps | G1: Expected result | H1: Status | I1: Priority | J1: Severity | K1: Actual result | L1: Comments
A2: NF-001 | B2: Responsive | C2: Mobile layout (360–768 px) | D2: Site loaded | E2: — | F2: 1. Resize to mobile. 2. Test menu, cart, checkout. | G2: Adaptive layout, mobile menu, usable checkout, collapsible admin menu. | H2: Fail | I2: High | J2: Major | K2: Aucun défilement horizontal à 360px sur l'accueil, mais /catalog à 360px déborde (scrollWidth 408 > 350) : le libellé 'PRÉCOMMANDE' d'une carte dépasse. | L2: Menu burger OK sur mobile. Checkout mobile à vérifier sur un vrai téléphone (la fenêtre du navigateur ne peut pas être redimensionnée ici, tests via iframe). [Claude (Cowork) — 27/09/2026]
A3: NF-002 | B3: Responsive | C3: Tablet & desktop | D3: Site loaded | E3: — | F3: 1. Test on tablet and wide desktop. | G3: Correct layout at all widths. | H3: Pass | I3: Medium | J3: Minor | K3: 768, 1280 et 1600px : pas de débordement, header complet, grilles 3/4/4 colonnes. | L3: [Claude (Cowork) — 27/09/2026]
A4: NF-003 | B4: Browsers | C4: Cross-browser compatibility | D4: Site loaded | E4: — | F4: 1. Test Chrome, Firefox, Safari, Edge. | G4: Identical behavior, no major regression. | H4: To test | I4: High | J4: Major
A5: NF-004 | B5: Performance | C5: Load time | D5: Site loaded | E5: — | F5: 1. Measure key page load times. | G5: Reasonable response, lazy-loaded admin (separate chunk). | H5: Fail | I5: Medium | J5: Minor | K5: TTFB 140 ms, DOMContentLoaded 0,8 s, load 2,1 s, LCP 2,2 s (bureau). Les images produit PNG pèsent 2,6 à 2,8 Mo CHACUNE. | L5: Convertir en WebP/AVIF ~100-200 Ko. Le preview sert un build de développement (bundle.js 2,8 Mo non découpé) : chunk admin séparé impossible à vérifier ici. [Claude (Cowork) — 27/09/2026]
A6: NF-005 | B6: Security | C6: CSP / cookies / CORS | D6: Production configured | E6: — | F6: 1. Check security headers + httpOnly cookie. | G6: CSP active, Secure/SameSite cookies, restricted CORS. | H6: Fail | I6: High | J6: Blocker | K6: API : CSP stricte, X-Frame-Options DENY, nosniff, HSTS, Referrer-Policy OK. Mais Access-Control-Allow-Origin: * sur l'API et aucune CSP sur les pages HTML. | L6: CORS * peut venir de l'environnement preview : à revérifier en production. Cookies httpOnly à vérifier une fois connecté. [Claude (Cowork) — 27/09/2026]
A7: NF-006 | B7: Security | C7: No secret exposed to client | D7: Site loaded | E7: — | F7: 1. Inspect network/console. | G7: No token/key (NOWPayments, Resend, admin) exposed to the browser. | H7: Pass | I7: High | J7: Blocker | K7: Aucune clé (NOWPayments, Resend, sk_…) trouvée dans le bundle JS ni dans la console. | L7: Le chemin secret /ops-portal-fn7k2q apparaît 3 fois dans le bundle ET dans l'URL publique /login?next=/ops-portal-fn7k2q (voir SP-014). [Claude (Cowork) — 27/09/2026]
A8: NF-007 | B8: Accessibility | C8: Keyboard navigation + ARIA labels | D8: Site loaded | E8: — | F8: 1. Browse with keyboard. | G8: Visible focus, labels/aria on key components. | H8: Fail | I8: Low | J8: Minor | K8: Les boutons +/− de quantité (fiche + panier) et tous les champs du checkout n'ont pas de nom accessible (pas de <label> lié ni d'aria-label). Le focus clavier est piégé nulle part : il traverse l'AgeGate et l'écran de refus. | L8: Test de focus visible non concluant via l'outil (la touche Tab de l'automate ne déplace pas le focus sur cette page). [Claude (Cowork) — 27/09/2026]
A9: NF-008 | B9: SEO | C9: robots.txt / sitemap (admin excluded) | D9: Production configured | E9: — | F9: 1. Check robots.txt and sitemap. | G9: Secret admin path neither indexed nor present. | H9: Pass | I9: Medium | J9: Minor | K9: robots.txt n'expose pas le chemin admin. Sitemap : 6 URL, pas d'admin. | L9: Le sitemap ne contient AUCUNE fiche produit (/product/...) : mauvais pour le SEO. robots.txt ne liste pas /affiliate ni /forgot-password. [Claude (Cowork) — 27/09/2026]
A10: NF-009 | B10: Resilience | C10: Network / API down | D10: Site loaded | E10: — | F10: 1. Cut the API. 2. Observe. | G10: Clean error (ErrorBoundary), no white screen. | H10: Blocked | I10: Medium | J10: Minor | K10: Impossible de couper l'API depuis le navigateur du testeur. | L10: À tester en arrêtant le backend du preview. [Claude (Cowork) — 27/09/2026]
A11: NF-010 | B11: i18n | C11: FR/EN consistency (all screens) | D11: Site loaded | E11: — | F11: 1. Toggle FR/EN on each page. | G11: No missing text, language mixing, or untranslated key. | H11: Fail | I11: High | J11: Major | K11: Aucun texte mélangé dans le corps des 15 routes testées en FR et EN. Mais les titres d'onglet restent en anglais en FR ('Catalog', 'About', 'Compliance', 'Privacy', 'Sign in', 'Register', 'Reset password', 'Affiliate Program Terms'). | L11: Checkout et accueil : titre générique anglais. L'écran de l'AgeGate est seulement en FR quand l'interface est en EN. [Claude (Cowork) — 27/09/2026]
